roblox_cloud_api/__init__.py
roblox_cloud_api/assets_api.py
roblox_cloud_api/key_api.py
roblox_cloud_api/open_cloud.py
roblox_cloud_api/user_api.py
roblox_cloud_api/common/__init__.py
roblox_cloud_api/common/rbxmk.py
roblox_cloud_api/common/rbxml.py
roblox_cloud_api/common/request.py
roblox_cloud_api/common/structs.py
roblox_cloud_api/common/utility.py
roblox_cloud_api-0.0.10.dist-info/LICENSE.txt
roblox_cloud_api-0.0.10.dist-info/METADATA
roblox_cloud_api-0.0.10.dist-info/WHEEL
roblox_cloud_api-0.0.10.dist-info/top_level.txt
roblox_cloud_api-0.0.10.dist-info/RECORD
