Metadata-Version: 2.1
Name: roblox-cloud-api
Version: 0.0.10
Summary: Roblox API for open cloud and assets.
Home-page: https://github.com/SPOOKEXE/PyPi_RobloxOpenCloud
Author: SPOOK_EXE (Declan)
License: MIT
Keywords: roblox,open-cloud,roblox open cloud,open cloud,roblox opencloud
Classifier: License :: OSI Approved :: MIT License
Classifier: Intended Audience :: Developers
Classifier: Programming Language :: Python :: 3 :: Only
Classifier: Operating System :: Microsoft :: Windows
Classifier: Operating System :: Unix
Classifier: Operating System :: MacOS :: MacOS X
Classifier: Development Status :: 2 - Pre-Alpha
License-File: LICENSE.txt
Requires-Dist: requests
Requires-Dist: pytest
